setup.py
pyanon/__init__.py
pyanon/chatsocket.py
pyanon/client.py
pyanon/httpclient.py
pyanon.egg-info/PKG-INFO
pyanon.egg-info/SOURCES.txt
pyanon.egg-info/dependency_links.txt
pyanon.egg-info/not-zip-safe
pyanon.egg-info/requires.txt
pyanon.egg-info/top_level.txt
pyanon/lib/__init__.py
pyanon/lib/postsearch.py
pyanon/lib/rocket/__init__.py
pyanon/lib/rocket/notification.py
pyanon/lib/rocket/notificationmessage.py
pyanon/lib/rocket/notificationpayload.py
pyanon/lib/rocket/notificationsender.py
pyanon/lib/rocket/rocketevent.py
pyanon/pkg/__init__.py
pyanon/pkg/exceptions/__init__.py
pyanon/pkg/exceptions/exceptionlist.py
pyanon/pkg/exceptions/utils.py
pyanon/pkg/exceptions/rocket/__init__.py
pyanon/pkg/exceptions/rocket/rocketexceptions.py
pyanon/pkg/exceptions/rocket/utils.py
pyanon/pkg/objects/__init__.py
pyanon/pkg/objects/account.py
pyanon/pkg/objects/comment.py
pyanon/pkg/objects/coordinates.py
pyanon/pkg/objects/page.py
pyanon/pkg/objects/picture.py
pyanon/pkg/objects/pictures.py
pyanon/pkg/objects/picturesize.py
pyanon/pkg/objects/post.py
pyanon/pkg/objects/postlist.py
pyanon/pkg/objects/response.py
pyanon/pkg/objects/rocketresponse.py
pyanon/pkg/objects/user.py
pyanon/pkg/objects/rocket/__init__.py
pyanon/pkg/objects/rocket/anonfields.py
pyanon/pkg/objects/rocket/channel.py
pyanon/pkg/objects/rocket/message.py
pyanon/pkg/objects/rocket/rocketuser.py
pyanon/pkg/objects/rocket/room.py
pyanon/pkg/objects/rocket/suggestedchannel.py
pyanon/pkg/utils/__init__.py
pyanon/pkg/utils/headers.py
pyanon/pkg/utils/objectification.py