Metadata-Version: 1.0
Name: pyanon
Version: 1.0
Summary: Api for new anonym client
Home-page: UNKNOWN
Author: UNKNOWN
Author-email: ktoya170214@gmail.com
License: UNKNOWN
Platform: UNKNOWN
